{
  "$schema": "https://context7.com/schema/context7.json",
  "projectTitle": "D-Sports Ecosystem Wallet",
  "description": "A comprehensive, multi-platform wallet SDK for React, Next.js, and React Native applications with custom social login functionality",
  "folders": [
    "src/core",
    "src/components",
    "src/hooks",
    "src/contexts",
    "src/utils",
    "src/services",
    "docs"
  ],
  "excludeFolders": [
    "archive",
    "archived",
    "old",
    "docs/old",
    "deprecated",
    "legacy",
    "previous",
    "outdated",
    "superseded",
    "i18n/zh*",
    "i18n/es*",
    "i18n/fr*",
    "i18n/de*",
    "i18n/ja*",
    "i18n/ko*",
    "i18n/ru*",
    "i18n/pt*",
    "i18n/it*",
    "i18n/ar*",
    "i18n/hi*",
    "i18n/tr*",
    "i18n/nl*",
    "i18n/pl*",
    "i18n/sv*",
    "i18n/vi*",
    "i18n/th*",
    "zh-cn",
    "zh-tw",
    "zh-hk",
    "zh-mo",
    "zh-sg",
    "node_modules",
    "dist",
    "logs"
  ],
  "excludeFiles": [
    "CHANGELOG.md",
    "changelog.md",
    "CHANGELOG.mdx",
    "changelog.mdx",
    "LICENSE.md",
    "license.md",
    "CODE_OF_CONDUCT.md",
    "code_of_conduct.md",
    "documentation-coverage-report.md"
  ],
  "rules": [
    "Use TypeScript with strict type checking",
    "Follow React 18+ best practices",
    "Use Ethers.js v6 for Ethereum interactions",
    "Use Zustand for state management",
    "Use Tailwind CSS for styling",
    "Use Radix UI for accessible component primitives",
    "Support multi-platform environments (Web/Next.js, React Native, Node.js)",
    "Follow the platform adapter pattern for cross-platform compatibility"
  ]
}